mosaicu.py
mosaicu-0.0.1.dist-info/METADATA
mosaicu-0.0.1.dist-info/WHEEL
mosaicu-0.0.1.dist-info/top_level.txt
mosaicu-0.0.1.dist-info/RECORD
