Metadata-Version: 2.1
Name: mosaicu
Version: 0.0.1
Summary: Mosaic an input picture.
Home-page: https://github.com/hanjoes/mosaicu
Author: hanjoes
Author-email: hanzhou87@gmail.com
License: UNKNOWN
Platform: UNKNOWN
Classifier: Programming Language :: Python :: 3.7
Classifier: License :: OSI Approved :: MIT License
Classifier: Operating System :: OS Independent
